[
  {
    "ucid": "2bb0b84a-8b11-456a-9d61-ff3f8b56449c",
    "transcript_length": 8467,
    "translation_length": 7201,
    "issues_count": 5,
    "churn_risk": 0.7,
    "churn_score_source": "gemini",
    "churn_score_rule_calculated": 0.8,
    "sentiment": "neutral -> frustrated",
    "sop_recommendations": 5,
    "success": true
  },
  {
    "ucid": "ec4ce354-cb34-46a1-81aa-1b301581948a",
    "success": false,
    "error": "{'message': 'value too long for type character varying(50)', 'code': '22001', 'hint': None, 'details': None}"
  },
  {
    "ucid": "fcbf0806-4564-4ee8-86c6-797ae35d401c",
    "transcript_length": 7034,
    "translation_length": 7183,
    "issues_count": 5,
    "churn_risk": 0.4,
    "churn_score_source": "gemini",
    "churn_score_rule_calculated": 0.05,
    "sentiment": "neutral -> satisfied",
    "sop_recommendations": 4,
    "success": true
  }
]